README.rst
feynmanium/__init__.py
feynmanium/__main__.py
feynmanium/base.py
feynmanium/cogs/__init__.py
feynmanium/cogs/calc.py
feynmanium/cogs/game.py
feynmanium/cogs/misc.py
feynmanium/cogs/trans.py
feynmanium/run.py
feynmanium-0.1.0.dist-info/entry_points.txt
feynmanium-0.1.0.dist-info/LICENSE
feynmanium-0.1.0.dist-info/WHEEL
feynmanium-0.1.0.dist-info/METADATA
feynmanium-0.1.0.dist-info/RECORD
