Metadata-Version: 2.1
Name: feynmanium
Version: 0.1.0
Summary: A discord bot that works.
Home-page: https://github.com/tb148/feynmanium
License: AGPL-3.0-or-later
Author: Tony Brown
Author-email: tb148@tuta.io
Requires-Python: >=3.10,<4.0
Classifier: License :: OSI Approved :: GNU Affero General Public License v3 or later (AGPLv3+)
Classifier: Programming Language :: Python :: 3
Classifier: Programming Language :: Python :: 3.10
Requires-Dist: CairoSVG (>=2.5.2,<3.0.0)
Requires-Dist: chess (>=1.9.2,<2.0.0)
Requires-Dist: discord.py (>=2.0.0,<3.0.0)
Requires-Dist: googletrans-py (>=4.0.0,<5.0.0)
Requires-Dist: mpmath (>=1.2.1,<2.0.0)
Requires-Dist: sympy (>=1.10.1,<2.0.0)
Requires-Dist: toml (>=0.10.2,<0.11.0)
Requires-Dist: tomlkit (>=0.11.4,<0.12.0)
Requires-Dist: uvloop (>=0.16.0,<0.17.0)
Project-URL: Repository, https://github.com/tb148/feynmanium
